Metadata-Version: 1.0
Name: temtek-distributions
Version: 0.1
Summary: Gaussian distributions and Binomial distributions
Home-page: UNKNOWN
Author: Temesghen Tekeste
Author-email: temesghen.dev@gmail.com
License: UNKNOWN
Platform: UNKNOWN
